sutekh/COPYING
sutekh/SutekhCli.py
sutekh/SutekhGui.py
sutekh/SutekhInfo.py
sutekh/SutekhUtility.py
sutekh/TestConsole.py
sutekh/__init__.py
sutekh/base/CliUtils.py
sutekh/base/Utility.py
sutekh/base/__init__.py
sutekh/base/core/BaseAbbreviations.py
sutekh/base/core/BaseAdapters.py
sutekh/base/core/BaseDBManagement.py
sutekh/base/core/BaseDatabaseUpgrade.py
sutekh/base/core/BaseFilters.py
sutekh/base/core/BaseGroupings.py
sutekh/base/core/BaseObjectMaker.py
sutekh/base/core/BaseTables.py
sutekh/base/core/CachedRelatedJoin.py
sutekh/base/core/CardLookup.py
sutekh/base/core/CardSetHolder.py
sutekh/base/core/CardSetUtilities.py
sutekh/base/core/DBSignals.py
sutekh/base/core/DBUtility.py
sutekh/base/core/DatabaseVersion.py
sutekh/base/core/FilterBox.py
sutekh/base/core/FilterParser.py
sutekh/base/core/ObjectCache.py
sutekh/base/core/__init__.py
sutekh/base/docs/DocUtils.py
sutekh/base/docs/__init__.py
sutekh/base/gui/AppMainWindow.py
sutekh/base/gui/AppMenu.py
sutekh/base/gui/AutoScrolledWindow.py
sutekh/base/gui/BaseCardTextFrame.py
sutekh/base/gui/BaseCardTextView.py
sutekh/base/gui/BaseConfigFile.py
sutekh/base/gui/BaseGuiDBManagement.py
sutekh/base/gui/BasePluginManager.py
sutekh/base/gui/BasicFrame.py
sutekh/base/gui/CachedIconManager.py
sutekh/base/gui/CardListFrame.py
sutekh/base/gui/CardListModel.py
sutekh/base/gui/CardListView.py
sutekh/base/gui/CardSetController.py
sutekh/base/gui/CardSetFrame.py
sutekh/base/gui/CardSetListModel.py
sutekh/base/gui/CardSetManagementController.py
sutekh/base/gui/CardSetManagementFrame.py
sutekh/base/gui/CardSetManagementMenu.py
sutekh/base/gui/CardSetManagementModel.py
sutekh/base/gui/CardSetManagementView.py
sutekh/base/gui/CardSetMenu.py
sutekh/base/gui/CardSetView.py
sutekh/base/gui/CardSetsListView.py
sutekh/base/gui/CellRendererIcons.py
sutekh/base/gui/CellRendererSutekhButton.py
sutekh/base/gui/CreateCardSetDialog.py
sutekh/base/gui/CustomDragIconView.py
sutekh/base/gui/DBUpgradeDialog.py
sutekh-2.2.0.dist-info/METADATA
sutekh-2.2.0.dist-info/WHEEL
sutekh-2.2.0.dist-info/entry_points.txt
sutekh-2.2.0.dist-info/top_level.txt
sutekh-2.2.0.dist-info/RECORD
