Metadata-Version: 2.4
Name: Sutekh
Version: 2.2.0
Summary: VtES Card Collection Manager
Home-page: https://sourceforge.net/projects/sutekh/
Download-URL: https://pypi.python.org/pypi/Sutekh/
Author: Simon Cross
Author-email: hodgestar+sutekh@gmail.com
Maintainer: Simon Cross
Maintainer-email: hodgestar+sutekh@gmail.com
License: GPL
Platform: Linux
Platform: Windows
Classifier: Development Status :: 4 - Beta
Classifier: Environment :: Console
Classifier: Environment :: Win32 (MS Windows)
Classifier: Environment :: X11 Applications :: GTK
Classifier: Intended Audience :: Developers
Classifier: Intended Audience :: End Users/Desktop
Classifier: License :: OSI Approved :: GNU General Public License (GPL)
Classifier: Operating System :: Microsoft :: Windows
Classifier: Operating System :: POSIX
Classifier: Programming Language :: Python :: 3.7
Classifier: Topic :: Games/Entertainment
Classifier: Topic :: Software Development :: Libraries :: Python Modules
Requires-Python: >=3
Requires-Dist: SQLObject>=3.0.0
Requires-Dist: ply
Requires-Dist: configobj
Requires-Dist: keyring
Dynamic: author
Dynamic: author-email
Dynamic: classifier
Dynamic: description
Dynamic: download-url
Dynamic: home-page
Dynamic: license
Dynamic: maintainer
Dynamic: maintainer-email
Dynamic: platform
Dynamic: requires-dist
Dynamic: requires-python
Dynamic: summary
